datareservoirio/__init__.py
datareservoirio/_constants.py
datareservoirio/_logging.py
datareservoirio/_utils.py
datareservoirio/appdirs.py
datareservoirio/authenticate.py
datareservoirio/client.py
datareservoirio/environments.py
datareservoirio/globalsettings.py
datareservoirio/storage/__init__.py
datareservoirio/storage/cache_engine.py
datareservoirio/storage/storage.py
datareservoirio-1.12.32.dist-info/licenses/LICENSE
datareservoirio-1.12.32.dist-info/METADATA
datareservoirio-1.12.32.dist-info/WHEEL
datareservoirio-1.12.32.dist-info/top_level.txt
datareservoirio-1.12.32.dist-info/RECORD
