Metadata-Version: 2.4
Name: datareservoirio
Version: 1.12.32
Summary: DataReservoir.io Python API
Author-email: 4Subsea <support@4subsea.com>
License: MIT License
Project-URL: Homepage, https://github.com/4Subsea/drio-python
Project-URL: Bug Tracker, https://github.com/4Subsea/drio-python/issues
Project-URL: Documentation, https://docs.4insight.io/dataanalytics/reservoir/python/latest/
Classifier: Development Status :: 5 - Production/Stable
Classifier: License :: OSI Approved :: MIT License
Classifier: Operating System :: OS Independent
Classifier: Programming Language :: Python :: 3.11
Classifier: Programming Language :: Python :: 3.12
Classifier: Programming Language :: Python :: 3.13
Requires-Python: <4,>=3.11
License-File: LICENSE
Requires-Dist: numpy
Requires-Dist: oauthlib
Requires-Dist: pandas
Requires-Dist: pyarrow
Requires-Dist: requests
Requires-Dist: requests-oauthlib
Requires-Dist: importlib_resources
Requires-Dist: tenacity<8.5
Requires-Dist: urllib3>2
Requires-Dist: tqdm
Requires-Dist: azure-monitor-opentelemetry==1.6.12
Dynamic: license-file
